[{"clue":"Set a price of","answer":"ASK"},{"clue":"Recede","answer":"EBB"},{"clue":"Arrange in folds","answer":"DRAPE"},{"clue":"They may hang out at pubs","answer":"BEERGUTS"},{"clue":"Brendan of “Crash”","answer":"FRASER"},{"clue":"Plain as day","answer":"CLEARCUT"},{"clue":"Way things look to the public, informally","answer":"OPTICS"},{"clue":"Buffalo’s N.H.L. team","answer":"SABRES"},{"clue":"Puffed snack food","answer":"RICECAKE"},{"clue":"Give the go-ahead","answer":"LET"},{"clue":"Revered Muslim","answer":"CALIPH"},{"clue":"Workers in puffy white hats","answer":"CHEFS"},{"clue":"Start of many young rappers’ names","answer":"LIL"},{"clue":"Intrinsically","answer":"PERSE"},{"clue":"2011 U.S. Open champ McIlroy","answer":"RORY"},{"clue":"Hazard for takeoffs and landings","answer":"FOG"},{"clue":"Astronomical streaker","answer":"METEOR"},{"clue":"Be behind, in a way","answer":"OWE"},{"clue":"Warrior","answer":"FIGHTER"},{"clue":"One of two in Princess Leia’s hairstyle","answer":"BUN"},{"clue":"Thornton ___, “Our Town” playwright","answer":"WILDER"},{"clue":"Tit for ___","answer":"TAT"},{"clue":"First lady Truman","answer":"BESS"},{"clue":"Daniel who wrote “Robinson Crusoe”","answer":"DEFOE"},{"clue":"“The Star-Spangled Banner” contraction","answer":"OER"},{"clue":"Key worker at a restaurant?","answer":"VALET"},{"clue":"Sources of saliva and sweat","answer":"GLANDS"},{"clue":"Slip up","answer":"ERR"},{"clue":"Game that requires bending","answer":"LEAPFROG"},{"clue":"Rude rejection","answer":"BITEME"},{"clue":"Duds","answer":"ATTIRE"},{"clue":"Sticker on green products","answer":"ECOLABEL"},{"clue":"Means of climbing over rural fences","answer":"STILES"},{"clue":"They can’t lose","answer":"SUREBETS"},{"clue":"One-on-one pupil","answer":"TUTEE"},{"clue":"Target of some football passes","answer":"END"},{"clue":"Spike of interest in movies?","answer":"LEE"},{"clue":"Some kindergarten lessons","answer":"ABCS"},{"clue":"Ward of “CSI: NY”","answer":"SELA"},{"clue":"Mascot on cookie boxes","answer":"KEEBLERELF"},{"clue":"Long-legged waders","answer":"EGRETS"},{"clue":"Florida gridders, in headlines","answer":"BUCS"},{"clue":"A/C measure, for short","answer":"BTU"},{"clue":"Forrest Gump’s favorite soft drink","answer":"DRPEPPER"},{"clue":"Gradually increase, with “up”","answer":"RATCHET"},{"clue":"Source of a big percentage of U.S. auto imports","answer":"ASIA"},{"clue":"Hunt-and-___ typing","answer":"PECK"},{"clue":"Gaelic tongue","answer":"ERSE"},{"clue":"Make thinner, as air","answer":"RAREFY"},{"clue":"Rulers, e.g. … or what the letters in 3-, 7-, 27- and 34-Down all have","answer":"STRAIGHTEDGES"},{"clue":"Points of convergence","answer":"FOCI"},{"clue":"Ailing","answer":"ILL"},{"clue":"Target of a plumber’s snake","answer":"CLOG"},{"clue":"Throng","answer":"CROWD"},{"clue":"Mandel of “America’s Got Talent”","answer":"HOWIE"},{"clue":"David Bowie hit with the lyric “You’ve torn your dress, your face is a mess”","answer":"REBELREBEL"},{"clue":"Boozehound","answer":"SOUSE"},{"clue":"Physicist Mach of Mach number fame","answer":"ERNST"},{"clue":"Many a Christmas tree","answer":"FIR"},{"clue":"Convened","answer":"MET"},{"clue":"“Be my guest!”","answer":"FEELFREE"},{"clue":"Blackens","answer":"TARS"},{"clue":"Group on top of a loose football","answer":"DOGPILE"},{"clue":"Bill for a 28-Down","answer":"BARTAB"},{"clue":"Yoko often seen in sunglasses","answer":"ONO"},{"clue":"Like some brides or threats","answer":"VEILED"},{"clue":"Bellicose Greek god","answer":"ARES"},{"clue":"Persist","answer":"LAST"},{"clue":"Rebuke to Brutus","answer":"ETTU"},{"clue":"Going ___ (bickering)","answer":"ATIT"},{"clue":"Brought into the world","answer":"BORN"},{"clue":"Ration, with “out”","answer":"METE"},{"clue":"Conditional word","answer":"ELSE"},{"clue":"Line that an actor waits to hear","answer":"CUE"}]