[{"clue":"Certain chemical weapon","answer":"GASBOMB"},{"clue":"Mars produces billions of them each week","answer":"MANDMS"},{"clue":"The Red Baron, for one","answer":"AVIATOR"},{"clue":"Like income from municipal bonds, usually","answer":"TAXFREE"},{"clue":"Iron compound found in steel","answer":"FERRITE"},{"clue":"Wrinkle, e.g.","answer":"AGELINE"},{"clue":"Island group near Dominica","answer":"FRENCHANTILLES"},{"clue":"Europe’s largest active volcano","answer":"ETNA"},{"clue":"Stop working","answer":"DIE"},{"clue":"Turf","answer":"SOD"},{"clue":"Truth ___","answer":"SERUM"},{"clue":"Org. concerned with reactions","answer":"NRC"},{"clue":"One with a beard","answer":"GOAT"},{"clue":"Option at many a fast-food restaurant","answer":"DRIVETHROUGH"},{"clue":"___ Fáil (Irish coronation stone)","answer":"LIA"},{"clue":"Reddit Q&A session, briefly","answer":"AMA"},{"clue":"Old Swedish coins","answer":"ORE"},{"clue":"Child’s Christmas wish","answer":"TOY"},{"clue":"Producer of horizontal shadows","answer":"SIDELIGHTING"},{"clue":"Rodrigo ___ de Vivar (El Cid)","answer":"DIAZ"},{"clue":"Exclaim","answer":"CRY"},{"clue":"Dance with a percussive effect","answer":"STOMP"},{"clue":"“Family Guy” daughter","answer":"MEG"},{"clue":"Nabokov novel","answer":"ADA"},{"clue":"Optima and Sedona","answer":"KIAS"},{"clue":"Arrive with fanfare … or what the shaded squares do?","answer":"MAKEANENTRANCE"},{"clue":"Not strict","answer":"LENIENT"},{"clue":"Unconventional soccer kick","answer":"TOEPOKE"},{"clue":"Does half of a mountaineering expedition","answer":"ASCENDS"},{"clue":"Poured out","answer":"EFFUSED"},{"clue":"Attack from a hiding place","answer":"WAYLAY"},{"clue":"Wooers","answer":"SUITORS"},{"clue":"TV debater’s worry","answer":"GAFFE"},{"clue":"Turns away","answer":"AVERTS"},{"clue":"Crumbly cheese similar to feta","answer":"SIRENE"},{"clue":"Women’s college affiliated with Columbia","answer":"BARNARD"},{"clue":"Suffix with psych-","answer":"OTIC"},{"clue":"___-eaten","answer":"MOTH"},{"clue":"“Cabbage”","answer":"BREAD"},{"clue":"Storied gift bearers","answer":"MAGI"},{"clue":"Ice skaters’ jumps","answer":"AXELS"},{"clue":"Image on the middle of a Super Bowl field","answer":"NFLLOGO"},{"clue":"Dehydrated","answer":"DRIEDOUT"},{"clue":"Clothing store department","answer":"MENS"},{"clue":"“You get me?”","answer":"SEE"},{"clue":"Food item sometimes called a “spud puppy”","answer":"TATERTOT"},{"clue":"Square after four","answer":"NINE"},{"clue":"Territory north of Afghanistan, in Risk","answer":"URAL"},{"clue":"Copy","answer":"MIMIC"},{"clue":"Captain America portrayer Evans","answer":"CHRIS"},{"clue":"Past","answer":"AGO"},{"clue":"Biblical possessive","answer":"THY"},{"clue":"Drifters","answer":"VAGRANTS"},{"clue":"$2 for Mediterranean Avenue, in Monopoly","answer":"RENT"},{"clue":"Drug taken in tabs","answer":"LSD"},{"clue":"Jr.’s junior","answer":"III"},{"clue":"Insistence","answer":"ADAMANCY"},{"clue":"Book after Lamentations","answer":"EZEKIEL"},{"clue":"Literary alter ego","answer":"HYDE"},{"clue":"Stop working","answer":"GOKAPUT"},{"clue":"Minnie who played in Major League Baseball in five different decades","answer":"MINOSO"},{"clue":"Winning player in Super Bowl I","answer":"PACKER"},{"clue":"Davis of “Thelma & Louise”","answer":"GEENA"},{"clue":"Preliminary payments","answer":"ANTES"},{"clue":"Gardener’s bagful","answer":"SEEDS"},{"clue":"___ Verde National Park","answer":"MESA"},{"clue":"Boy who owns Buzz Lightyear and Woody","answer":"ANDY"},{"clue":"Food sold in blocks","answer":"TOFU"},{"clue":"Mortgage adjustment, for short","answer":"REFI"},{"clue":"Case study?","answer":"LAW"}]