[{"clue":"Gift from Jacob to Joseph, in the Bible ","answer":" COAT"},{"clue":"Projecting arm of a crane ","answer":" JIB"},{"clue":"Metropolitan address abbr. ","answer":" APTNO"},{"clue":"Prefix with conservative ","answer":" ARCH"},{"clue":"___ Tesfaye, real name of singer The Weeknd ","answer":" ABEL"},{"clue":"Sun deck? ","answer":" TAROT"},{"clue":"Pet-friendly org. ","answer":" SPCA"},{"clue":"They're usually caught lying down ","answer":" ZEES"},{"clue":"Hurdles for would-be G.P.s ","answer":" MCATS"},{"clue":"Bouncer who can always spot a fake? ","answer":" THEWIZARDOFID"},{"clue":"\"Wicked cool!\" ","answer":" RAD"},{"clue":"Cinephile's channel ","answer":" TCM"},{"clue":"Fall of Troy escapee ","answer":" AENEAS"},{"clue":"Low-scoring soccer win ","answer":" ONENIL"},{"clue":"Backstory for TV's Magnum? ","answer":" LIFEOFPI"},{"clue":"Egyptian protector of tombs ","answer":" ANUBIS"},{"clue":"Go (for) ","answer":" OPT"},{"clue":"Advice for how the pope can reach out online? ","answer":" IMABELIEVER"},{"clue":"Nick or ding ","answer":" MAR"},{"clue":"Churchill's successor in 1945 ","answer":" ATTLEE"},{"clue":"Statement before \"... and that's Canada!\"? ","answer":" THISISUS"},{"clue":"Recruit ","answer":" ENLIST"},{"clue":"Hindu protector of the universe ","answer":" VISHNU"},{"clue":"Triage pro, for short ","answer":" EMT"},{"clue":"French 101 pronoun ","answer":" TOI"},{"clue":"Certain people prefer their computer specialists to be attractive? ","answer":" SOMELIKEITHOT"},{"clue":"Bean harvested by the Aztecs ","answer":" CACAO"},{"clue":"Churchill's successor in 1955 ","answer":" EDEN"},{"clue":"Hankering ","answer":" WANT"},{"clue":"Kazakhstan range ","answer":" URALS"},{"clue":"It's nice when it's forgiven ","answer":" DEBT"},{"clue":"Cold, cold drink ","answer":" ICEE"},{"clue":"Surrealist Max ","answer":" ERNST"},{"clue":"Part of GPS: Abbr. ","answer":" SYS"},{"clue":"\"One From the Heart\" actress, 1982 ","answer":" GARR"},{"clue":"Democratic politico Julián ","answer":" CASTRO"},{"clue":"Harry Potter, e.g. ","answer":" ORPHAN"},{"clue":"Consent (to) ","answer":" ACCEDE"},{"clue":"Détente ","answer":" THAW"},{"clue":"Where cats play? ","answer":" JAZZCLUB"},{"clue":"Letter-shaped construction piece ","answer":" IBEAM"},{"clue":"\"Hold my ___\" (words before a foolish act) ","answer":" BEER"},{"clue":"Money paid to get more money ","answer":" ATMFEE"},{"clue":"Hollywood star whose birth name is Alfredo ","answer":" PACINO"},{"clue":"Acquire midseason, as a sports team might ","answer":" TRADEFOR"},{"clue":"What \"!\" can mean in computer programming ","answer":" NOT"},{"clue":"Post-regulation periods, for short ","answer":" OTS"},{"clue":"Pitcher Dock Ellis claimed to have used this before throwing a no-hitter in 1970 ","answer":" LSD"},{"clue":"1986 music memoir ","answer":" ITINA"},{"clue":"Lummox ","answer":" OAF"},{"clue":"Whats next? ","answer":" APP"},{"clue":"Canine command ","answer":" SIT"},{"clue":"Service site for many a vet ","answer":" NAM"},{"clue":"Light airs ","answer":" LILTS"},{"clue":"Doubter's question ","answer":" ISIT"},{"clue":"One looking for a match? ","answer":" BEAU"},{"clue":"Biometric reading ","answer":" IRISSCAN"},{"clue":"What B and C (but not A) may represent ","answer":" ELEMENTS"},{"clue":"Starbucks size ","answer":" VENTI"},{"clue":"Long-bodied predator ","answer":" EEL"},{"clue":"Sister channel of VH1 ","answer":" MTV"},{"clue":"Yellowfin tuna ","answer":" AHI"},{"clue":"Nautical chart markings ","answer":" SHOALS"},{"clue":"Deepest, as feelings ","answer":" INMOST"},{"clue":"Refuse to settle ","answer":" SUE"},{"clue":"College town located, appropriately, near Ulysses, N.Y. ","answer":" ITHACA"},{"clue":"Oklahoma athlete ","answer":" SOONER"},{"clue":"Half-laugh ","answer":" TITTER"},{"clue":"Just make it ","answer":" EKEBY"},{"clue":"Showed the way ","answer":" LED"},{"clue":"Shakespearean warning word ","answer":" IDES"},{"clue":"Bit of kindling ","answer":" TWIG"},{"clue":"\"That's my ___!\" ","answer":" CUE"},{"clue":"Abbr. on a music score ","answer":" ARR"}]