[{"clue":"Obtain with difficulty ","answer":" TRACKDOWN"},{"clue":"You can't make one by yourself ","answer":" DEAL"},{"clue":"Place where you pay for what you break ","answer":" REPAIRSHOP"},{"clue":"Villain who says \"What you know, you know\" ","answer":" IAGO"},{"clue":"\"Wow\" ","answer":" IMPRESSIVE"},{"clue":"See 19-Across ","answer":" STEW"},{"clue":"___ bourguignon (variety of 18-Across) ","answer":" BOEUF"},{"clue":"A symbol of Australia ","answer":" OPAL"},{"clue":"The Taj Mahal or Great Pyramid ","answer":" TOMB"},{"clue":"It usually leaves crumbs ","answer":" ERASER"},{"clue":"Baby buggy? ","answer":" LARVAL"},{"clue":"Very rich ","answer":" CALORIFIC"},{"clue":"Not level with ","answer":" LIETO"},{"clue":"Biblical mount ","answer":" ASS"},{"clue":"Group that's on the take? ","answer":" CAMERACREW"},{"clue":"Left, and then some ","answer":" SOCIALIST"},{"clue":"Reading, to Brits ","answer":" MAJORINGIN"},{"clue":"Show dejection, in a way ","answer":" SAG"},{"clue":"Yawning, but not from boredom ","answer":" AGAPE"},{"clue":"Spot starter? ","answer":" TEAKETTLE"},{"clue":"James who is more than a little forward? ","answer":" LEBRON"},{"clue":"\"You got that right!\" ","answer":" SUREDO"},{"clue":"Sun bloc? ","answer":" WNBA"},{"clue":"Island off the Tuscan coast ","answer":" ELBA"},{"clue":"Tenderer, maybe ","answer":" RIPER"},{"clue":"What results from an ace on a deuce ","answer":" ADIN"},{"clue":"Making rough ","answer":" COARSENING"},{"clue":"City near Sparks ","answer":" RENO"},{"clue":"Role for which LeVar Burton was nominated for an Emmy ","answer":" KUNTAKINTE"},{"clue":"Rowers' workout machines, informally ","answer":" ERGS"},{"clue":"Hoi polloi ","answer":" THEMASSES"},{"clue":"Noted film festival site since 2002 ","answer":" TRIBECA"},{"clue":"Suckerfish ","answer":" REMORAS"},{"clue":"Reacts to losing one's hearing, perhaps ","answer":" APPEALS"},{"clue":"Performer in the first U.S. public radio broadcast, 1910 ","answer":" CARUSO"},{"clue":"Actor Sutherland ","answer":" KIEFER"},{"clue":"Profs, often ","answer":" DRS"},{"clue":"Italian menu palindrome ","answer":" OSSO"},{"clue":"First object made by humans to break the sound barrier ","answer":" WHIP"},{"clue":"Flare way up? ","answer":" NOVA"},{"clue":"What a representative represents ","answer":" DISTRICT"},{"clue":"Have dinner at a friend's ","answer":" EATOVER"},{"clue":"Contemporary ","answer":" AGEMATE"},{"clue":"\"That was uncalled for\" ","answer":" LOWBLOW"},{"clue":"Kind of grant ","answer":" PELL"},{"clue":"Actress Christina ","answer":" RICCI"},{"clue":"\"I'm afraid ...\" ","answer":" ALAS"},{"clue":"Barely perceptible ","answer":" FAINT"},{"clue":"Something that might need polishing ","answer":" IMAGE"},{"clue":"Salsa legend Cruz ","answer":" CELIA"},{"clue":"Blues venues? ","answer":" RINKS"},{"clue":"TV Guide's \"Best Series of All Time,\" with \"The\" ","answer":" SOPRANOS"},{"clue":"Froyo mix-in ","answer":" OREO"},{"clue":"Apple worms, say ","answer":" MALWARE"},{"clue":"Like some nonbinary people ","answer":" AGENDER"},{"clue":"Poking vigorously ","answer":" JABBING"},{"clue":"Laceless footwear ","answer":" STEPINS"},{"clue":"Having a little chewiness ","answer":" ALDENTE"},{"clue":"1960s-'70s French president Pompidou ","answer":" GEORGES"},{"clue":"Exuberant cry ","answer":" EUREKA"},{"clue":"Some Caribbean islanders ","answer":" TRINIS"},{"clue":"Make out ","answer":" NECK"},{"clue":"Lug ","answer":" LOUT"},{"clue":"___ mi (Vietnamese sandwich) ","answer":" BANH"},{"clue":"Uffizi Gallery holding ","answer":" ARTE"},{"clue":"Houston, for one ","answer":" SAM"}]