[{"clue":"Share on social media ","answer":" POST"},{"clue":"Blackens ","answer":" CHARS"},{"clue":"Screen org.? ","answer":" TSA"},{"clue":"William H. Bonney ___ Billy the Kid ","answer":" AKA"},{"clue":"Mathematician taught by Bernoulli ","answer":" EULER"},{"clue":"Most populous nation not in the U.N. ","answer":" TAIWAN"},{"clue":"Best Actress winner of 1999 and 2004 ","answer":" HILARYSWANK"},{"clue":"It's just part of the act ","answer":" SCENE"},{"clue":"Surname of Princess Leia ","answer":" ORGANA"},{"clue":"Midwest college town ","answer":" AMESIOWA"},{"clue":"\"Curiouser and curiouser ...\" ","answer":" THEPLOTTHICKENS"},{"clue":"Bother ","answer":" EATAT"},{"clue":"Grand onstage ","answer":" PIANO"},{"clue":"Place to swim or work out, informally ","answer":" THEY"},{"clue":"Business that has cut prices ","answer":" SALON"},{"clue":"Entertaining ","answer":" OPENTO"},{"clue":"Went over the limit, say ","answer":" SPED"},{"clue":"Major name in petrol ","answer":" ESSO"},{"clue":"Language from which \"jackal\" and \"jasmine\" come ","answer":" FARSI"},{"clue":"\"La Traviata\" composer ","answer":" VERDI"},{"clue":"Jeer ","answer":" SCOFF"},{"clue":"Bit on a book jacket ","answer":" BIO"},{"clue":"Part of a three-in-a-row ","answer":" TAC"},{"clue":"Greasy in the Pro Football Hall of Fame ","answer":" NEALE"},{"clue":"In-group at school ","answer":" POPULARKIDS"},{"clue":"Preach the gospel ","answer":" EVANGELIZE"},{"clue":"Rip off ","answer":" ROB"},{"clue":"Longtime \"All Things Considered\" host Robert ","answer":" SIEGEL"},{"clue":"Screenwriter Ephron ","answer":" NORA"},{"clue":"Anchor, e.g. ","answer":" LEG"},{"clue":"Chinese liquor made from sorghum ","answer":" MAOTAI"},{"clue":"\"Consequently ...\" ","answer":" ANDSO"},{"clue":"Verbal alternative to a shoulder tap ","answer":" PSST"},{"clue":"Beginnings of ideas ","answer":" GERMS"},{"clue":"Internet content typically viewed alone ","answer":" PORN"},{"clue":"Italian scooter brand ","answer":" VESPA"},{"clue":"What 1-Down has that 1-Across lacks ","answer":" SHORTE"},{"clue":"Part of the resistance? ","answer":" OHM"},{"clue":"Some pickup info on rideshare apps: Abbr. ","answer":" ETDS"},{"clue":"Stir ","answer":" EXCITE"},{"clue":"Man's name that means \"my God\" ","answer":" ELI"},{"clue":"What's depicted by the circled letters in 41-/49-Across ","answer":" OFFONALARK"},{"clue":"... in 52-Across ","answer":" SPREADEAGLE"},{"clue":"Rehearse a play from start to finish, in theater lingo ","answer":" RUNIT"},{"clue":"Swimmer in a Himeji Castle moat ","answer":" KOI"},{"clue":"Nursery floor hazard ","answer":" TOY"},{"clue":"Unfamiliar with ","answer":" NEWTO"},{"clue":"Informal \"What if ...?\" ","answer":" SPOSE"},{"clue":"Alter, as a manuscript ","answer":" EMEND"},{"clue":"Bird's home ","answer":" NEST"},{"clue":"Bird's home ","answer":" CAGE"},{"clue":"Places for speakers ","answer":" DAISES"},{"clue":"Common people ","answer":" PLEBS"},{"clue":"Close up, say ","answer":" HEAL"},{"clue":"Stylish ballroom dance ","answer":" SALSA"},{"clue":"Investigation ","answer":" PROBE"},{"clue":"... in 25-Across ","answer":" HEADLESSCHICKEN"},{"clue":"Brown powder ","answer":" COCOAMIX"},{"clue":"French cake ","answer":" GATEAU"},{"clue":"Nashville university, familiarly ","answer":" VANDY"},{"clue":"... and in 19-Across ","answer":" SWANDIVE"},{"clue":"Go to ","answer":" ATTEND"},{"clue":"Princess of Avalor, in children's TV ","answer":" ELENA"},{"clue":"Machiavellian ","answer":" SLY"},{"clue":"Tape deck button ","answer":" REC"},{"clue":"Oboes and saxes, e.g. ","answer":" REEDS"},{"clue":"Aid for a detective ","answer":" LEAD"},{"clue":"Real pain ","answer":" PEST"},{"clue":"Reaction to pain ","answer":" OUCH"},{"clue":"Berth place ","answer":" SLEEPERCAR"},{"clue":"Bowling ","answer":" TENPINS"},{"clue":"Cause of a supermarket parking mishap ","answer":" CART"},{"clue":"Tripping ","answer":" HIGH"},{"clue":"Expected ","answer":" AWAITED"},{"clue":"Serving with carrots and celery, maybe ","answer":" RANCHDIP"},{"clue":"Meander ","answer":" SNAKE"},{"clue":"Lighter-air link ","answer":" THAN"},{"clue":"Virtual people ","answer":" SIMS"},{"clue":"Bitter, e.g. ","answer":" ALE"},{"clue":"Alternative to Times New Roman ","answer":" ARIAL"},{"clue":"Noncapital city whose name means \"capital city\" ","answer":" KYOTO"},{"clue":"City on the Nile ","answer":" ASWAN"},{"clue":"As (to) ","answer":" RELATING"},{"clue":"Band with the 1983 #1 hit \"Africa\" ","answer":" TOTO"},{"clue":"Far offshore ","answer":" ASEA"},{"clue":"Kit ___ ","answer":" KAT"},{"clue":"Dedicator of Iceland's Imagine Peace Tower ","answer":" ONO"},{"clue":"Ocelli ","answer":" EYESPOTS"},{"clue":"Challenges for movers ","answer":" SOFAS"},{"clue":"Habitually ","answer":" OFTEN"},{"clue":"___ Nurmi, 1920s Olympic runner nicknamed the \"Flying Finn\" ","answer":" PAAVO"},{"clue":"Bud of baseball ","answer":" SELIG"},{"clue":"Veep's boss ","answer":" PREZ"},{"clue":"Subject of lessons at an island resort ","answer":" SCUBA"},{"clue":"Roman sun god ","answer":" SOL"},{"clue":"Team at an upscale restaurant ","answer":" VALETS"},{"clue":"Brother ","answer":" FRIAR"},{"clue":"Cowboy's home, informally ","answer":" BIGD"},{"clue":"Middle of the month ","answer":" IDES"},{"clue":"Best Play Tony winner with a geographical name ","answer":" OSLO"},{"clue":"Jellied delicacies ","answer":" EELS"},{"clue":"Cry from Juliet ","answer":" OROMEO"},{"clue":"___ club (annual show presenter) ","answer":" KENNEL"},{"clue":"Diaper, in Britspeak ","answer":" NAPPIE"},{"clue":"Chef Lagasse ","answer":" EMERIL"},{"clue":"Crossword constructing, e.g. (no, really!) ","answer":" ART"},{"clue":"AirPod pairing target ","answer":" IPHONE"},{"clue":"\"Paradise Lost\" tempter ","answer":" SATAN"},{"clue":"Site of Jesus' crucifixion ","answer":" GOLGOTHA"},{"clue":"Prefix with directional ","answer":" OMNI"},{"clue":"Word with life or flak ","answer":" VEST"},{"clue":"Brand of markers ","answer":" EXPO"},{"clue":"See the future with a crystal ball ","answer":" SCRY"},{"clue":"Track meet divisions ","answer":" HEATS"},{"clue":"Worth keeping around ","answer":" OFUSE"},{"clue":"Peacefully protests, as during the national anthem ","answer":" TAKESAKNEE"},{"clue":"Flier on a mission ","answer":" DRONE"},{"clue":"Loses traction ","answer":" SKIDS"},{"clue":"Pristine places ","answer":" EDENS"},{"clue":"Fairy tale alter ego ","answer":" FROG"},{"clue":"Crushed in competition ","answer":" ATEALIVE"},{"clue":"Pronoun in a picture rebus ","answer":" EWE"},{"clue":"Increase quickly ","answer":" ESCALATE"},{"clue":"Mixing board ","answer":" PALETTE"},{"clue":"Wrongly predict, as an election ","answer":" MISCALL"},{"clue":"Dit's partner ","answer":" DAH"},{"clue":"Places for figureheads ","answer":" PROWS"},{"clue":"Not express ","answer":" LOCAL"},{"clue":"Magazine that named Barack Obama its first-ever Person of the Year (2009) ","answer":" EBONY"},{"clue":"Bit of sweat ","answer":" BEAD"},{"clue":"\"J. ___\" (2011 Clint Eastwood biopic) ","answer":" EDGAR"},{"clue":"Missile first used in the Yom Kippur War ","answer":" SCUD"},{"clue":"Non-Macs ","answer":" PCS"},{"clue":"Kind of mind ","answer":" HIVE"},{"clue":"Suit ","answer":" EXEC"},{"clue":"Number in brackets? ","answer":" SEED"},{"clue":"Without ","answer":" SANS"},{"clue":"Poet ___ St. Vincent Millay ","answer":" EDNA"},{"clue":"Diana who was the first person to swim from Cuba to Florida without the aid of shark protection (2013) ","answer":" NYAD"},{"clue":"Russian for \"peace\" ","answer":" MIR"}]