{"grid":[["#","#","N","O","M","#","#"],["#","P","O","P","I","N","#"],["D","A","T","E","N","U","T"],["I","R","O","N","O","R","E"],["F","A","N","T","A","S","Y"],["#","S","C","O","N","E","#"],["#","#","E","E","S","#","#"]],"width":7,"height":7,"entries":[{"row":0,"col":2,"direction":"Across","length":3,"number":1,"clue":"Bit of Oscar recognition, informally"},{"row":0,"col":2,"direction":"Down","length":7,"number":1,"clue":"Never ever"},{"row":0,"col":3,"direction":"Down","length":7,"number":2,"clue":"Type of sandal"},{"row":0,"col":4,"direction":"Down","length":7,"number":3,"clue":"Ancient inhabitants of Crete"},{"row":1,"col":1,"direction":"Across","length":5,"number":4,"clue":"Drop by unexpectedly"},{"row":1,"col":1,"direction":"Down","length":5,"number":4,"clue":"Legal assistants, for short"},{"row":1,"col":5,"direction":"Down","length":5,"number":5,"clue":"One taking vitals, perhaps"},{"row":2,"col":0,"direction":"Down","length":3,"number":6,"clue":"\"What's the ___?\""},{"row":2,"col":0,"direction":"Across","length":7,"number":6,"clue":"Kind of bread"},{"row":2,"col":6,"direction":"Down","length":3,"number":7,"clue":"Josephine who wrote \"The Daughter of Time\""},{"row":3,"col":0,"direction":"Across","length":7,"number":8,"clue":"Raw material for steel"},{"row":4,"col":0,"direction":"Across","length":7,"number":9,"clue":"Genre for the Harry Potter books"},{"row":5,"col":1,"direction":"Across","length":5,"number":10,"clue":"British biscuit"},{"row":6,"col":2,"direction":"Across","length":3,"number":11,"clue":"Many Caltech grads, for short"}]}