[{"clue":"Things kindergartners learn ","answer":" ABCS"},{"clue":"In addition ","answer":" ALSO"},{"clue":"\"The Naked ___\" (Goya painting) ","answer":" MAJA"},{"clue":"Bit of snow ","answer":" FLAKE"},{"clue":"What some bills become ","answer":" LAWS"},{"clue":"Burden ","answer":" ONUS"},{"clue":"Dog-___ (like some old book pages) ","answer":" EARED"},{"clue":"\"Told ya!\" ","answer":" ICALLEDIT"},{"clue":"With 37- and 52-Across, #11 on the American Film Institute's \"100 Years ... 100 Movie Quotes\" list ","answer":" WHATWEVEGOT"},{"clue":"Freezerful ","answer":" ICE"},{"clue":"Put in a bibliography ","answer":" CITE"},{"clue":"Have the wheel ","answer":" STEER"},{"clue":"\"Rebecca\" author Du Maurier ","answer":" DAPHNE"},{"clue":"The \"Homo\" in Homo sapiens ","answer":" GENUS"},{"clue":"In the past ","answer":" AGO"},{"clue":"Former lovers ","answer":" OLDFLAMES"},{"clue":"See 20-Across ","answer":" HEREISFAILURETO"},{"clue":"Accepts begrudgingly, as a minor flaw ","answer":" LETSSLIDE"},{"clue":"___TV (Time Warner channel) ","answer":" TRU"},{"clue":"Casting assignments ","answer":" PARTS"},{"clue":"Meryl who portrayed Margaret Thatcher ","answer":" STREEP"},{"clue":"43rd U.S. president, informally ","answer":" DUBYA"},{"clue":"One of 18 on an 18-wheeler ","answer":" TIRE"},{"clue":"Bear: Sp. ","answer":" OSO"},{"clue":"See 20-Across ","answer":" COMMUNICATE"},{"clue":"Make over ","answer":" REFASHION"},{"clue":"Winter drink ","answer":" COCOA"},{"clue":"Data ","answer":" INFO"},{"clue":"Plains tribe ","answer":" OTOE"},{"clue":"Drug bust units ","answer":" KILOS"},{"clue":"With 66- and 67-Across, source of this puzzle theme's quote ","answer":" COOL"},{"clue":"See 65-Across ","answer":" HAND"},{"clue":"See 65-Across ","answer":" LUKE"},{"clue":"Two or three ","answer":" AFEW"},{"clue":"Ho-hum ","answer":" BLAH"},{"clue":"___ mia (Italian term of endearment) ","answer":" CARA"},{"clue":"Quick drawing ","answer":" SKETCH"},{"clue":"___ and kicking ","answer":" ALIVE"},{"clue":"One poked through the eye? ","answer":" LACE"},{"clue":"Free goodies at an event ","answer":" SWAG"},{"clue":"Nobel Peace Prize city ","answer":" OSLO"},{"clue":"\"The Simpsons\" bartender ","answer":" MOE"},{"clue":"Actress MacDowell of \"Four Weddings and a Funeral\" ","answer":" ANDIE"},{"clue":"Electricity, slangily ","answer":" JUICE"},{"clue":"Fall bloomer ","answer":" ASTER"},{"clue":"Olympic hurdler Moses ","answer":" EDWIN"},{"clue":"Shipmate of Capt. Kirk and Mr. Spock ","answer":" LTSULU"},{"clue":"Summer in France ","answer":" ETE"},{"clue":"Peter the Great, e.g. ","answer":" TSAR"},{"clue":"Author Roald ","answer":" DAHL"},{"clue":"Pulitzer Prize-winning author James ","answer":" AGEE"},{"clue":"City with piers ","answer":" PORT"},{"clue":"Alternatives to mums ","answer":" GLADS"},{"clue":"\"The Sopranos\" Emmy winner Falco ","answer":" EDIE"},{"clue":"Packers' and Panthers' org. ","answer":" NFL"},{"clue":"\"Make ___ what you will\" ","answer":" OFIT"},{"clue":"Portion (out) ","answer":" METE"},{"clue":"Raison d'___ ","answer":" ETRE"},{"clue":"Campbell's product ","answer":" SOUP"},{"clue":"Athletic achievement award ","answer":" ESPY"},{"clue":"Susan with the 1978 best seller \"Compromising Positions\" ","answer":" ISAACS"},{"clue":"Camera type, for short ","answer":" SLR"},{"clue":"Something confessed in a confessional ","answer":" SIN"},{"clue":"Pulling a rabbit out of a hat, e.g. ","answer":" TRICK"},{"clue":"Pull back, as in horror ","answer":" RECOIL"},{"clue":"Kind of column in architecture ","answer":" DORIC"},{"clue":"\"___ hooks\" (shipping caution) ","answer":" USENO"},{"clue":"Highly successful, in theaterspeak ","answer":" BOFFO"},{"clue":"Readied, as a musical instrument ","answer":" TUNED"},{"clue":"Cry of anticipation ","answer":" OHOH"},{"clue":"Big name in photocopiers, once ","answer":" MITA"},{"clue":"Where the U.S. flag has flown since 1969 ","answer":" MOON"},{"clue":"Anticensorship org. ","answer":" ACLU"},{"clue":"Swiped ","answer":" TOOK"},{"clue":"Abate ","answer":" EASE"},{"clue":"\"You've got mail\" co. ","answer":" AOL"}]