[{"clue":"Get in the game?","answer":"ANTE"},{"clue":"Home of the comics heroes Asterix and Obelix","answer":"GAUL"},{"clue":"Month with a so-called “hunter’s moon”: Abbr.","answer":"OCT"},{"clue":"“Let’s Make ___”","answer":"ADEAL"},{"clue":"Actor Edward James ___","answer":"OLMOS"},{"clue":"“It’s cold in here!”","answer":"BRR"},{"clue":"What might be rolled for a strike","answer":"BOWLINGBALL"},{"clue":"Put (down)","answer":"LAY"},{"clue":"___ no good (misbehaving)","answer":"UPTO"},{"clue":"Bud … or bait","answer":"CHUM"},{"clue":"Slightly off","answer":"AMISS"},{"clue":"Verse in a poem","answer":"STANZA"},{"clue":"What a clock might strike","answer":"MIDNIGHT"},{"clue":"[A spider!]","answer":"EEK"},{"clue":"___ Fleming, British naval intelligence officer-turned-writer","answer":"IAN"},{"clue":"Is on the same page","answer":"AGREES"},{"clue":"Dexterous","answer":"DEFT"},{"clue":"Milky gem","answer":"OPAL"},{"clue":"Put two and two together, say","answer":"ADD"},{"clue":"What might strike during a storm","answer":"LIGHTNING"},{"clue":"Mermaid’s home","answer":"SEA"},{"clue":"Place for a fork … or a jackknife?","answer":"ROAD"},{"clue":"Cry of pain","answer":"YELP"},{"clue":"Popular Nissan model","answer":"MAXIMA"},{"clue":"“For sure!”","answer":"YES"},{"clue":"Ctrl-___-Del","answer":"ALT"},{"clue":"Who might go on strike","answer":"EMPLOYEE"},{"clue":"Plush fabric","answer":"VELOUR"},{"clue":"Religious believer of a sort","answer":"DEIST"},{"clue":"Rod between wheels","answer":"AXLE"},{"clue":"Site for buying and selling crafts","answer":"ETSY"},{"clue":"Letters on a Forever stamp","answer":"USA"},{"clue":"What might strike you while solving this puzzle","answer":"INSPIRATION"},{"clue":"6-3 in tennis, e.g.","answer":"SET"},{"clue":"Place to leave one’s shoes, perhaps","answer":"FOYER"},{"clue":"Disney heroine whose name means “ocean”","answer":"MOANA"},{"clue":"Firefighter’s tool","answer":"AXE"},{"clue":"Many a big charity event","answer":"GALA"},{"clue":"“Bird by Bird” writer Lamott","answer":"ANNE"},{"clue":"Took home a “furever friend,” say","answer":"ADOPTED"},{"clue":"Fresh spin on a familiar concept","answer":"NEWTAKE"},{"clue":"Prey-catching claw","answer":"TALON"},{"clue":"Inventor Whitney","answer":"ELI"},{"clue":"Painter Vincent van ___","answer":"GOGH"},{"clue":"Lady Gaga’s “The Fame” or “Artpop”","answer":"ALBUM"},{"clue":"It’s not sweet, sour, salty or bitter","answer":"UMAMI"},{"clue":"Response to a funny text (that usually isn’t literally true)","answer":"LOL"},{"clue":"Beholden (to)","answer":"OBLIGED"},{"clue":"Suddenly stopped working, as a computer","answer":"CRASHED"},{"clue":"Secret meetings","answer":"TRYSTS"},{"clue":"Mistreat","answer":"ABUSE"},{"clue":"Sort of language generally found in Urban Dictionary","answer":"SLANG"},{"clue":"Final Four org.","answer":"NCAA"},{"clue":"Desert illusion","answer":"MIRAGE"},{"clue":"Rigatoni relative","answer":"ZITI"},{"clue":"Surrealist Salvador","answer":"DALI"},{"clue":"Manhattan neighborhood containing some of N.Y.U.","answer":"NOHO"},{"clue":"Thrashes about","answer":"FLAILS"},{"clue":"Org. that provides chaperones for field trips","answer":"PTA"},{"clue":"Name on Woody’s shoe in “Toy Story”","answer":"ANDY"},{"clue":"Overcast","answer":"GRAY"},{"clue":"Wall Street inits. since 1792","answer":"NYSE"},{"clue":"Like some couples","answer":"SAMESEX"},{"clue":"Atone for","answer":"EXPIATE"},{"clue":"Mekong Valley resident","answer":"LAOTIAN"},{"clue":"Wedding guest’s partner, say","answer":"PLUSONE"},{"clue":"Only mortal Gorgon in Greek myth","answer":"MEDUSA"},{"clue":"Recurring theme","answer":"MOTIF"},{"clue":"Penultimate word in a fairy tale","answer":"EVER"},{"clue":"Attempting to, casually","answer":"TRYNA"},{"clue":"G.P.A. booster","answer":"EASYA"},{"clue":"Kick out","answer":"EXPEL"},{"clue":"Divulge","answer":"LETON"},{"clue":"Pre-euro currency","answer":"LIRA"},{"clue":"Christmastime concoction","answer":"NOG"},{"clue":"Doctors’ org.","answer":"AMA"}]