[{"clue":"Easy way to ease pain","answer":"POPAPILL"},{"clue":"Doesn’t bother","answer":"LETSBE"},{"clue":"About a third of South America","answer":"AMAZONIA"},{"clue":"Election Day declaration","answer":"IVOTED"},{"clue":"Tries to detect, as a substance in the body","answer":"TESTSFOR"},{"clue":"Literally, “of nothing”","answer":"DENADA"},{"clue":"Part of some shortcuts","answer":"ALT"},{"clue":"Its capital is Nuku’alofa","answer":"TONGA"},{"clue":"“Dagnabbit!”","answer":"NERTS"},{"clue":"Bottom of the sea?","answer":"KEEL"},{"clue":"Single numbers","answer":"SOLI"},{"clue":"Trash holder","answer":"BIN"},{"clue":"“How curious …”","answer":"ITSODD"},{"clue":"Final stage","answer":"ENDGAME"},{"clue":"Fan favorite","answer":"CROWDPLEASER"},{"clue":"Patronize off-track betting, say","answer":"PLAYTHEPONIES"},{"clue":"Blockbuster 2014 animated film","answer":"THELEGOMOVIE"},{"clue":"Typing center","answer":"HOMEROW"},{"clue":"Heat","answer":"ESTRUS"},{"clue":"Repeated collaborator with Bowie","answer":"ENO"},{"clue":"Grasslands burrower","answer":"VOLE"},{"clue":"Supposed source of large footprints","answer":"YETI"},{"clue":"The “00” of “.00”","answer":"CENTS"},{"clue":"V-shaped cut","answer":"NOTCH"},{"clue":"In","answer":"HOT"},{"clue":"The Beatles had their last one in 1966","answer":"USTOUR"},{"clue":"2014 Facebook acquisition","answer":"WHATSAPP"},{"clue":"Not leave at the end of the line","answer":"REELIN"},{"clue":"One of the superstates in “1984”","answer":"EASTASIA"},{"clue":"Panegyrizes","answer":"EXALTS"},{"clue":"Instagram rival","answer":"SNAPCHAT"},{"clue":"Republican politico George","answer":"PATAKI"},{"clue":"___ station","answer":"OMELET"},{"clue":"Wallops","answer":"PASTES"},{"clue":"Drug marketed as Retrovir","answer":"AZT"},{"clue":"Use Instagram, e.g.","answer":"POST"},{"clue":"Thumbnail bio, e.g.","answer":"INFO"},{"clue":"Threats to Daniel, in the Book of Daniel","answer":"LIONS"},{"clue":"Slow and dignified","answer":"LARGO"},{"clue":"Aid in keeping food fresh","answer":"LID"},{"clue":"Perfectly matched","answer":"EVEN"},{"clue":"Word with skin or ring","answer":"TONE"},{"clue":"Outpost in science fiction","answer":"STARBASE"},{"clue":"Subjects of babysitter negotiations","answer":"BEDTIMES"},{"clue":"Portrayer of Warren Buffett in HBO’s “Too Big to Fail”","answer":"EDASNER"},{"clue":"War-torn Mideast city","answer":"ALEPPO"},{"clue":"Setting","answer":"LOCALE"},{"clue":"Smitten","answer":"INLOVE"},{"clue":"Lint collector","answer":"DRYER"},{"clue":"End of a presidential address","answer":"DOTGOV"},{"clue":"Margaret Thatcher’s husband","answer":"DENIS"},{"clue":"Merrymaking","answer":"GAIETY"},{"clue":"Question pundits discuss after a presidential debate","answer":"WHOWON"},{"clue":"Certain voter ID","answer":"DEM"},{"clue":"Intimate practice done at a distance","answer":"PHONESEX"},{"clue":"Beverage said to help with weight loss","answer":"LEMONTEA"},{"clue":"“Friday I’m in Love” band, 1992","answer":"THECURE"},{"clue":"Warmed-over material","answer":"REHASH"},{"clue":"It’s perfect","answer":"UTOPIA"},{"clue":"Hold tight","answer":"SITPAT"},{"clue":"“Never stop improving” sloganeer","answer":"LOWES"},{"clue":"___ Hunt, protagonist in the “Mission: Impossible” films","answer":"ETHAN"},{"clue":"Payment that many wait in line to make","answer":"TOLL"},{"clue":"“___ yourself”","answer":"SUIT"},{"clue":"Mexican quarters","answer":"CASA"},{"clue":"Letters before a colon","answer":"HTTP"},{"clue":"Some shelter volunteers, briefly","answer":"RNS"},{"clue":"Certain ink holder","answer":"SAC"}]