[{"clue":"No credit, say","answer":"CASHONLY"},{"clue":"Cause of a public embarrassment, maybe","answer":"HOTMIC"},{"clue":"“Please, go ahead”","answer":"AFTERYOU"},{"clue":"Blitz","answer":"INVADE"},{"clue":"Flop","answer":"LAYANEGG"},{"clue":"What fools do, they say","answer":"RUSHIN"},{"clue":"Bank job of a sort","answer":"REPO"},{"clue":"Things kept on racks","answer":"BIKES"},{"clue":"Spreadsheet entries: Abbr.","answer":"NOS"},{"clue":"Walks slowly and steadily","answer":"TROOPS"},{"clue":"Stuff","answer":"SATE"},{"clue":"Wall Street woe","answer":"LOSS"},{"clue":"Alternative to a Yodel or a Swiss Roll","answer":"HOHO"},{"clue":"Fool","answer":"SIMP"},{"clue":"Pacific Northwest native","answer":"CHINOOK"},{"clue":"Picketer’s holding","answer":"PLACARD"},{"clue":"Joan who wrote “The Year of Magical Thinking”","answer":"DIDION"},{"clue":"Outburst from Sneezy","answer":"AHCHOO"},{"clue":"Like ziggurats","answer":"STEPPED"},{"clue":"This will help ease the pain","answer":"TYLENOL"},{"clue":"“___ All That” (1999 rom-com)","answer":"SHES"},{"clue":"Haydée, to the Count of Monte Cristo, par exemple","answer":"AMIE"},{"clue":"Cockamamie","answer":"DAFT"},{"clue":"Very bright, but not in a good way","answer":"LOUD"},{"clue":"New Age author Deepak ___","answer":"CHOPRA"},{"clue":"Two for dinner?","answer":"ENS"},{"clue":"First in a series","answer":"PILOT"},{"clue":"Close one","answer":"CHUM"},{"clue":"2015 film from Marvel Studios","answer":"ANTMAN"},{"clue":"Affecting people at large","answer":"SOCIETAL"},{"clue":"Where Marie Curie was born","answer":"POLAND"},{"clue":"Bit of misdirection from an athlete","answer":"HEADFAKE"},{"clue":"Clearly working out","answer":"SWEATY"},{"clue":"Generic rivalry","answer":"USVSTHEM"},{"clue":"___ State (school with 23 campuses)","answer":"CAL"},{"clue":"Way out there","answer":"AFAR"},{"clue":"Diagnosis from an ophthalmologist","answer":"STYE"},{"clue":"Great deal","answer":"HEAP"},{"clue":"Expression of doubt","answer":"ORNOT"},{"clue":"Day when the ball drops: Abbr.","answer":"NYE"},{"clue":"Ship’s record","answer":"LOGBOOK"},{"clue":"Trading card franchise that’s an alternative to Pokémon","answer":"YUGIOH"},{"clue":"Like good computer screens, for short","answer":"HIRES"},{"clue":"Weight","answer":"ONUS"},{"clue":"Array in a security office","answer":"TVS"},{"clue":"Muppets song with nonsense lyrics","answer":"MAHNAMAHNA"},{"clue":"Impossible to screw up","answer":"IDIOTPROOF"},{"clue":"Fill with fragrance, in a way","answer":"CENSE"},{"clue":"Music genre for Psy and BTS","answer":"KPOP"},{"clue":"Côtes du ___ (wine appellation)","answer":"RHONE"},{"clue":"Released for attack","answer":"SICCED"},{"clue":"Features of some 11-Down","answer":"LCDS"},{"clue":"“Here comes a fight!”","answer":"OHITSONNOW"},{"clue":"Extra work","answer":"SIDEHUSTLE"},{"clue":"Bid at the last second","answer":"SNIPED"},{"clue":"Political satirist who said “If you were the only person left on the planet, I would have to attack you. That’s my job”","answer":"SAHL"},{"clue":"Accident report?","answer":"OOPS"},{"clue":"Mantle, e.g.","answer":"LAYER"},{"clue":"Fool","answer":"DOLT"},{"clue":"Author whose name is one letter off from 31-Down","answer":"DAHL"},{"clue":"Acts cautiously (around)","answer":"TIPTOES"},{"clue":"Kind of pork","answer":"MOOSHU"},{"clue":"Bounds","answer":"LEAPS"},{"clue":"___ Williams, player of Shirley on “Laverne & Shirley”","answer":"CINDY"},{"clue":"They’re not basic","answer":"ACIDS"},{"clue":"Huff and puff","answer":"PANT"},{"clue":"Weight","answer":"HEFT"},{"clue":"Home to part of the Wasatch Mountains","answer":"UTAH"},{"clue":"“___ me!”","answer":"MAKE"},{"clue":"Barnyard sound","answer":"MAA"},{"clue":"Eastern Central Div. player","answer":"CAV"},{"clue":"Apollo craft, for short","answer":"LEM"}]