[{"clue":"Bill Bryson book subtitled \"Rediscovering America on the Appalachian Trail\" ","answer":" AWALKINTHEWOODS"},{"clue":"Give a scolding ","answer":" CALLONTHECARPET"},{"clue":"Show whose logo replaces an \"o\" with a diamond ring ","answer":" THEBACHELORETTE"},{"clue":"Actress Rowlands ","answer":" GENA"},{"clue":"Look after ","answer":" MIND"},{"clue":"Head for a cow, horse or lion? ","answer":" SEA"},{"clue":"Book often stored horizontally ","answer":" ATLAS"},{"clue":"Put a strain on ","answer":" TAX"},{"clue":"Short jazz riff ","answer":" LICK"},{"clue":"Johnny with 10 World Series of Poker bracelets ","answer":" CHAN"},{"clue":"Reading area ","answer":" DEN"},{"clue":"Spoils ","answer":" TAINTS"},{"clue":"Mother of the four winds, in myth ","answer":" EOS"},{"clue":"Cut off the back ","answer":" BEEFLOIN"},{"clue":"High-risk game ","answer":" RUSSIANROULETTE"},{"clue":"Many national anthems ","answer":" WARSONGS"},{"clue":"\"Errare humanum ___\" ","answer":" EST"},{"clue":"\"Whatever works\" ","answer":" IMEASY"},{"clue":"Indifferent remark ","answer":" MEH"},{"clue":"Hurdle for a future atty. ","answer":" LSAT"},{"clue":"Something you're not likely to fork out? ","answer":" SOUP"},{"clue":"Seventh word of the Gettysburg Address ","answer":" OUR"},{"clue":"Home to the Imam Ali Mosque, built in the seventh century ","answer":" BASRA"},{"clue":"___ Reactor (Iron Man's power source) ","answer":" ARC"},{"clue":"Weathered, say ","answer":" WORN"},{"clue":"\"Je t'___\" ","answer":" AIME"},{"clue":"Products of Under Armour and Nike ","answer":" ATHLETICAPPAREL"},{"clue":"\"Could you give more detail?\" ","answer":" CARETOELABORATE"},{"clue":"Certain summer attire ","answer":" SLEEVELESSDRESS"},{"clue":"Enter the picture? ","answer":" ACT"},{"clue":"Muted trumpet sound ","answer":" WAH"},{"clue":"Pub container ","answer":" ALEGLASS"},{"clue":"Claim to fame for Freeport, Me. ","answer":" LLBEAN"},{"clue":"Zen riddles ","answer":" KOANS"},{"clue":"People who built the Qhapaq Ñan, or \"Royal Road,\" which stretched roughly 3,700 miles ","answer":" INCA"},{"clue":"High degree ","answer":" NTH"},{"clue":"1960s spy series ","answer":" THEMANFROMUNCLE"},{"clue":"Path an electron may take moving in a constant magnetic field ","answer":" HELIX"},{"clue":"Nobel Prize subj. ","answer":" ECON"},{"clue":"City section ","answer":" WARD"},{"clue":"Lucky strike ","answer":" ORE"},{"clue":"Gets on a mailing list, say ","answer":" OPTSIN"},{"clue":"Pick up ","answer":" DETECT"},{"clue":"Hearty dinner entrees ","answer":" STEAKS"},{"clue":"Big name in laptops ","answer":" ACER"},{"clue":"Grand ","answer":" THOU"},{"clue":"Much of Gen Alpha, now ","answer":" TEENS"},{"clue":"Train route ","answer":" LINE"},{"clue":"Hon ","answer":" DEARY"},{"clue":"Unsparing response to a complaint ","answer":" TOUGH"},{"clue":"Isn't 100% ","answer":" AILS"},{"clue":"Slant ","answer":" BIAS"},{"clue":"Not a company person? ","answer":" LONER"},{"clue":"Substitute ","answer":" SWAP"},{"clue":"Mosaic tiles ","answer":" TESSERAE"},{"clue":"Romanov V.I.P. ","answer":" TSAR"},{"clue":"___ Candy, best friend of Wonder Woman ","answer":" ETTA"},{"clue":"Jason who played Lucius Malfoy in Harry Potter films ","answer":" ISAACS"},{"clue":"Plaything for a Greek god ","answer":" MORTAL"},{"clue":"Trump is named in it ","answer":" EUCHRE"},{"clue":"Delilah player in 1949's \"Samson and Delilah\" ","answer":" LAMARR"},{"clue":"Large bay window projecting from a wall ","answer":" ORIEL"},{"clue":"Two-legged stand ","answer":" BIPOD"},{"clue":"Cable channel owned by AMC Networks ","answer":" WETV"},{"clue":"Great Plains people ","answer":" OTOE"},{"clue":"Police dept. alerts ","answer":" APBS"},{"clue":"Rebecca ___ Crumpler, first African-American female physician in the U.S. ","answer":" LEE"},{"clue":"Small cells ","answer":" AAS"},{"clue":"Org. that administers the G.R.E. ","answer":" ETS"},{"clue":"French article ","answer":" LES"}]