[{"clue":"Grp. from which many people are drafted ","answer":" NCAA"},{"clue":"Twosome on TMZ ","answer":" ITEM"},{"clue":"Longtime members of the bar? ","answer":" SOTS"},{"clue":"Clumsy sorts ","answer":" OAFS"},{"clue":"___ Scotia ","answer":" NOVA"},{"clue":"Old print tint ","answer":" SEPIA"},{"clue":"Groundskeeper's supply ","answer":" GRASSSEED"},{"clue":"Rome's ___ Fountain ","answer":" TREVI"},{"clue":"Narrow passage for ships ","answer":" STRAIT"},{"clue":"\"Aquí se habla ___\" ","answer":" ESPANOL"},{"clue":"\"Play it by ear\" or \"see eye to eye\" ","answer":" IDIOM"},{"clue":"\"Dragnet\" force, briefly ","answer":" LAPD"},{"clue":"\"Do my eyes deceive me?!\" ","answer":" WELLLOOKYTHERE"},{"clue":"Health class subject ","answer":" SEX"},{"clue":"Actress Kemper of \"Unbreakable Kimmy Schmidt\" ","answer":" ELLIE"},{"clue":"Alpine goat ","answer":" IBEX"},{"clue":"\"Guernica\" artist ","answer":" PICASSO"},{"clue":"It goes from 0 to 14, in chemistry ","answer":" PHSCALE"},{"clue":"Lab assistant in many a horror film ","answer":" IGOR"},{"clue":"Birth-related ","answer":" NATAL"},{"clue":"Periodically tugging on one's ear, say ","answer":" TIC"},{"clue":"Hearty breakfast order ","answer":" THREEEGGOMELET"},{"clue":"Actors McShane and McKellen ","answer":" IANS"},{"clue":"Follow ","answer":" ENSUE"},{"clue":"Alarm ","answer":" STARTLE"},{"clue":"Reach ","answer":" ATTAIN"},{"clue":"Concert pianist Rubinstein ","answer":" ARTUR"},{"clue":"Hit 1980s-'90s sitcom ... or what the circled letters in 16-, 26- and 43-Across represent? ","answer":" FULLHOUSE"},{"clue":"Military action that includes a blockade ","answer":" SIEGE"},{"clue":"Arizona's Agua ___ National Monument ","answer":" FRIA"},{"clue":"Ash containers ","answer":" URNS"},{"clue":"Groundskeepers' supplies ","answer":" SODS"},{"clue":"Conveyance used either lying down or sitting up ","answer":" SLED"},{"clue":"Pictures created with needles, informally ","answer":" TATS"},{"clue":"Some holiday concoctions ","answer":" NOGS"},{"clue":"Sight at a golf course or grocery ","answer":" CART"},{"clue":"In the distance ","answer":" AFAR"},{"clue":"Lay into ","answer":" ASSAIL"},{"clue":"Inculcates ","answer":" INSTILLS"},{"clue":"\"Piggy\" ","answer":" TOE"},{"clue":"Preceding day ","answer":" EVE"},{"clue":"Earned ","answer":" MADE"},{"clue":"Blissfully serene ","answer":" SERAPHIC"},{"clue":"Expression of opinion from all sides ","answer":" OPENDEBATE"},{"clue":"Big name in DVRs ","answer":" TIVO"},{"clue":"It's rigged ","answer":" SAIL"},{"clue":"March honoree, for short ","answer":" STPAT"},{"clue":"Moves like a crab ","answer":" SIDLES"},{"clue":"Crafty ","answer":" SLY"},{"clue":"Tea choice ","answer":" OOLONG"},{"clue":"\"Voulez-vous coucher avec ___?\" ","answer":" MOI"},{"clue":"Consider in detail, as options ","answer":" WEIGH"},{"clue":"Censured ","answer":" EXCORIATED"},{"clue":"Didn't stop ","answer":" KEPTON"},{"clue":"Kindled anew ","answer":" RELIT"},{"clue":"Prez, e.g. ","answer":" EXEC"},{"clue":"Pig roast need ","answer":" SPIT"},{"clue":"Throws on the floor? ","answer":" AREARUGS"},{"clue":"Nonkosher deli offering ","answer":" HAMSALAD"},{"clue":"Nancy Drew, for one ","answer":" SLEUTH"},{"clue":"What a tree's rings signify ","answer":" AGE"},{"clue":"___ nous ","answer":" ENTRE"},{"clue":"Night school subj. ","answer":" ESL"},{"clue":"Free from a cage ","answer":" LETOUT"},{"clue":"Lip or cheek ","answer":" SASS"},{"clue":"Huey, Dewey and Louie, e.g. ","answer":" TRIO"},{"clue":"Lots of fluff? ","answer":" EFFS"},{"clue":"Ambience ","answer":" AURA"},{"clue":"\"___ that something?!\" ","answer":" ISNT"},{"clue":"Eliot of the Untouchables ","answer":" NESS"},{"clue":"\"www\" address ","answer":" URL"},{"clue":"\"This is not the last clue in this puzzle,\" e.g. ","answer":" LIE"}]