{"grid":[["#","#","N","F","L","#","#"],["#","S","A","T","E","S","#"],["S","I","M","C","I","T","Y"],["U","D","E","#","S","O","R"],["M","E","D","I","U","M","S"],["#","B","A","S","R","A","#"],["#","#","Y","P","E","#","#"]],"width":7,"height":7,"entries":[{"row":0,"col":2,"direction":"Across","length":3,"number":1,"clue":"Org. whose participants wear helmets"},{"row":0,"col":2,"direction":"Down","length":7,"number":1,"clue":"Catholic celebration"},{"row":0,"col":3,"direction":"Down","length":3,"number":2,"clue":"Antitrust law enforcement org."},{"row":0,"col":4,"direction":"Down","length":7,"number":3,"clue":"Sports & ___ (Trivial Pursuit category)"},{"row":1,"col":1,"direction":"Across","length":5,"number":4,"clue":"Leaves full"},{"row":1,"col":1,"direction":"Down","length":5,"number":4,"clue":"Lesser-played part of a record, usually"},{"row":1,"col":5,"direction":"Down","length":5,"number":5,"clue":"Botanical opening"},{"row":2,"col":0,"direction":"Down","length":3,"number":6,"clue":"Redundant word in front of “total”"},{"row":2,"col":0,"direction":"Across","length":7,"number":6,"clue":"Pioneering building game for computers"},{"row":2,"col":6,"direction":"Down","length":3,"number":7,"clue":"Info next to alumni names, maybe: Abbr."},{"row":3,"col":0,"direction":"Across","length":3,"number":8,"clue":"Ulan-___, Siberian capital"},{"row":3,"col":4,"direction":"Across","length":3,"number":9,"clue":"Frat.’s counterpart"},{"row":4,"col":0,"direction":"Across","length":7,"number":10,"clue":"Dead ringers?"},{"row":4,"col":3,"direction":"Down","length":3,"number":11,"clue":"AOL, e.g."},{"row":5,"col":1,"direction":"Across","length":5,"number":12,"clue":"Home to the Imam Ali Mosque, built in the seventh century"},{"row":6,"col":2,"direction":"Across","length":3,"number":13,"clue":"FaceTime alternative"}]}