{"grid":[["#","#","A","V","E","#","#"],["#","C","R","E","M","A","#"],["P","L","U","G","I","N","S"],["B","O","G","#","R","Y","E"],["A","D","U","L","A","T","E"],["#","S","L","O","T","H","#"],["#","#","A","M","I","#","#"]],"width":7,"height":7,"entries":[{"row":0,"col":2,"direction":"Across","length":3,"number":1,"clue":"Manhattan’s Madison or Lexington: Abbr."},{"row":0,"col":2,"direction":"Down","length":7,"number":1,"clue":"Peppery salad green"},{"row":0,"col":3,"direction":"Down","length":3,"number":2,"clue":"Do nothin’"},{"row":0,"col":4,"direction":"Down","length":7,"number":3,"clue":"Certain native of the Mideast"},{"row":1,"col":1,"direction":"Across","length":5,"number":4,"clue":"Espresso foam"},{"row":1,"col":1,"direction":"Down","length":5,"number":4,"clue":"Idiots"},{"row":1,"col":5,"direction":"Down","length":5,"number":5,"clue":"Insurance giant based in Hartford"},{"row":2,"col":0,"direction":"Down","length":3,"number":6,"clue":"Grp. concerned with gutters and pins"},{"row":2,"col":0,"direction":"Across","length":7,"number":6,"clue":"Software add-ons that offer extra features"},{"row":2,"col":6,"direction":"Down","length":3,"number":7,"clue":"“Get it now?”"},{"row":3,"col":0,"direction":"Across","length":3,"number":8,"clue":"Locale for moss"},{"row":3,"col":4,"direction":"Across","length":3,"number":9,"clue":"City on the New York/Connecticut border"},{"row":4,"col":0,"direction":"Across","length":7,"number":10,"clue":"Put on a pedestal"},{"row":4,"col":3,"direction":"Down","length":3,"number":11,"clue":"Herbert of the “Pink Panther” films"},{"row":5,"col":1,"direction":"Across","length":5,"number":12,"clue":"Laziest of the deadly sins"},{"row":6,"col":2,"direction":"Across","length":3,"number":13,"clue":"“Who ___?” (amnesiac’s query)"}]}