{"grid":[["#","#","O","O","X","#","#"],["#","S","H","I","F","T","#"],["H","E","M","L","I","N","E"],["A","N","Y","#","N","O","I"],["D","O","G","S","I","T","S"],["#","R","O","U","T","E","#"],["#","#","D","R","Y","#","#"]],"width":7,"height":7,"entries":[{"row":0,"col":2,"direction":"Across","length":3,"number":1,"clue":"It's for naught in noughts-and-crosses"},{"row":0,"col":2,"direction":"Down","length":7,"number":1,"clue":"\"Holy moly!\""},{"row":0,"col":3,"direction":"Down","length":3,"number":2,"clue":"What a dipstick measures the level of"},{"row":0,"col":4,"direction":"Down","length":7,"number":3,"clue":"Comcast subsidiary"},{"row":1,"col":1,"direction":"Across","length":5,"number":4,"clue":"Work period"},{"row":1,"col":1,"direction":"Down","length":5,"number":4,"clue":"Mister, south of the border"},{"row":1,"col":5,"direction":"Down","length":5,"number":5,"clue":"Fed. bond"},{"row":2,"col":0,"direction":"Down","length":3,"number":6,"clue":"Consumed"},{"row":2,"col":0,"direction":"Across","length":7,"number":6,"clue":"The difference between a mini and a midi"},{"row":2,"col":6,"direction":"Down","length":3,"number":7,"clue":"German winter hazard"},{"row":3,"col":0,"direction":"Across","length":3,"number":8,"clue":"\"___ takers?\""},{"row":3,"col":4,"direction":"Across","length":3,"number":9,"clue":"\"There's ___ in team\""},{"row":4,"col":0,"direction":"Across","length":7,"number":10,"clue":"Watches Bowser, say"},{"row":4,"col":3,"direction":"Down","length":3,"number":11,"clue":"Direction opposite norte"},{"row":5,"col":1,"direction":"Across","length":5,"number":12,"clue":"Delivery person's assignment"},{"row":6,"col":2,"direction":"Across","length":3,"number":13,"clue":"Like deserts and some humor"}]}