{"grid":[["U","F","O","#","G","D","R"],["P","U","B","#","O","T","O"],["S","N","L","H","O","S","T"],["#","#","I","U","D","#","#"],["D","O","G","M","A","T","A"],["A","S","E","#","I","C","C"],["H","E","D","#","M","M","L"]],"width":7,"height":7,"entries":[{"row":0,"col":0,"direction":"Across","length":3,"number":1,"clue":"1950s Project Blue Book subject, for short"},{"row":0,"col":0,"direction":"Down","length":3,"number":1,"clue":"Chin-___"},{"row":0,"col":1,"direction":"Down","length":3,"number":2,"clue":"“Sounds like a good time!”"},{"row":0,"col":2,"direction":"Down","length":7,"number":3,"clue":"Beholden (to)"},{"row":0,"col":4,"direction":"Across","length":3,"number":4,"clue":"Warsaw Pact member west of Poland, for short"},{"row":0,"col":4,"direction":"Down","length":7,"number":4,"clue":"What a three-point shooter needs"},{"row":0,"col":5,"direction":"Down","length":3,"number":5,"clue":"Rehab woe, for short"},{"row":0,"col":6,"direction":"Down","length":3,"number":6,"clue":"“Poppycock!”"},{"row":1,"col":0,"direction":"Across","length":3,"number":7,"clue":"Mag, e.g."},{"row":1,"col":4,"direction":"Across","length":3,"number":8,"clue":"Prefix with laryngology"},{"row":2,"col":0,"direction":"Across","length":7,"number":9,"clue":"Alec Baldwin, on more than 15 occasions"},{"row":2,"col":3,"direction":"Down","length":3,"number":10,"clue":"Bees make it"},{"row":3,"col":2,"direction":"Across","length":3,"number":11,"clue":"Contraceptive insert, in brief"},{"row":4,"col":0,"direction":"Down","length":3,"number":12,"clue":"“Zip-a-Dee-Doo-___”"},{"row":4,"col":0,"direction":"Across","length":7,"number":12,"clue":"Doctrines"},{"row":4,"col":1,"direction":"Down","length":3,"number":13,"clue":"Suffix with lact-"},{"row":4,"col":5,"direction":"Down","length":3,"number":14,"clue":"Channel for lovers of old films"},{"row":4,"col":6,"direction":"Down","length":3,"number":15,"clue":"Knee part, for short"},{"row":5,"col":0,"direction":"Across","length":3,"number":16,"clue":"Suffix with carboxyl"},{"row":5,"col":4,"direction":"Across","length":3,"number":17,"clue":"Govt. watchdog until 1996"},{"row":6,"col":0,"direction":"Across","length":3,"number":18,"clue":"“If only ___ listened …”"},{"row":6,"col":4,"direction":"Across","length":3,"number":19,"clue":"Midcentury year"}]}